django_auto_modeladmin/__init__.py
django_auto_modeladmin/main.py
django_auto_modeladmin/utils.py
django_auto_modeladmin-0.1.12.dist-info/METADATA
django_auto_modeladmin-0.1.12.dist-info/RECORD
django_auto_modeladmin-0.1.12.dist-info/WHEEL
django_auto_modeladmin-0.1.12.dist-info/top_level.txt
