Metadata-Version: 2.1
Name: django-auto-modeladmin
Version: 0.1.12
Summary: Automatically creates a ModelAdmin for each model instance passed in a list.
Home-page: https://github.com/alexseitsinger/django_auto_modeladmin
Author: Alex Seitsinger
Author-email: alexseitsinger@gmail.com
License: BSD 2-Clause License
Platform: UNKNOWN
Classifier: Development Status :: 3 - Alpha
Classifier: Intended Audience :: Developers
Classifier: Topic :: Utilities
Classifier: Programming Language :: Python
Classifier: Programming Language :: Python :: 3
Classifier: Programming Language :: Python :: 3.3
Classifier: Programming Language :: Python :: 3.4
Classifier: Programming Language :: Python :: 3.5
Classifier: Programming Language :: Python :: 3.6
Classifier: License :: OSI Approved :: BSD License
Requires-Dist: Django (>=2.0)
Requires-Dist: django-nested-admin
